README.rst
setup.py
fixedwidthtext/__init__.py
fixedwidthtext/exceptions.py
fixedwidthtext/fields.py
fixedwidthtext/models.py
fixedwidthtext.egg-info/PKG-INFO
fixedwidthtext.egg-info/SOURCES.txt
fixedwidthtext.egg-info/dependency_links.txt
fixedwidthtext.egg-info/requires.txt
fixedwidthtext.egg-info/top_level.txt