Metadata-Version: 1.1
Name: fixedwidthtext
Version: 0.1
Summary: Library to extract data from semi-structured text documents
Home-page: http://github.org/lopinho/fixedwidthtext
Author: André Ferreira
Author-email: lopinho@gmail.com
License: MIT
Platform: UNKNOWN
Classifier: Development Status :: 3 - Alpha
Classifier: Intended Audience :: Developers
Classifier: License :: OSI Approved :: MIT License
Classifier: Operating System :: OS Independent
Classifier: Programming Language :: Python :: 2.7
Classifier: Programming Language :: Python :: 3.3
Classifier: Topic :: Software Development :: Libraries :: Python Modules
